.coveragerc
.gitignore
CHANGES.rst
LICENSE.txt
MANIFEST.in
README.rst
TODO.txt
setup.py
tox.ini
src/pjpersist/README.txt
src/pjpersist/__init__.py
src/pjpersist/datamanager.py
src/pjpersist/interfaces.py
src/pjpersist/mapping.py
src/pjpersist/mquery.py
src/pjpersist/patch.py
src/pjpersist/persistent.py
src/pjpersist/pool.py
src/pjpersist/querystats.py
src/pjpersist/serialize.py
src/pjpersist/serializers.py
src/pjpersist/sqlbuilder.py
src/pjpersist/testing.py
src/pjpersist.egg-info/PKG-INFO
src/pjpersist.egg-info/SOURCES.txt
src/pjpersist.egg-info/dependency_links.txt
src/pjpersist.egg-info/entry_points.txt
src/pjpersist.egg-info/not-zip-safe
src/pjpersist.egg-info/requires.txt
src/pjpersist.egg-info/top_level.txt
src/pjpersist/tests/__init__.py
src/pjpersist/tests/json_speed_test.py
src/pjpersist/tests/performance.py
src/pjpersist/tests/random_data.py
src/pjpersist/tests/random_data_generator.py
src/pjpersist/tests/test_datamanager.py
src/pjpersist/tests/test_doc.py
src/pjpersist/tests/test_mapping.py
src/pjpersist/tests/test_mquery.py
src/pjpersist/tests/test_mquery_db.py
src/pjpersist/tests/test_querystats.py
src/pjpersist/tests/test_serialize.py
src/pjpersist/tests/test_serialize_db.py
src/pjpersist/tests/test_sqlbuilder.py
src/pjpersist/zope/__init__.py
src/pjpersist/zope/annotation.py
src/pjpersist/zope/container.py
src/pjpersist/zope/dublincore.py
src/pjpersist/zope/interfaces.py
src/pjpersist/zope/schema.py
src/pjpersist/zope/tests/__init__.py
src/pjpersist/zope/tests/test_container.py