Metadata-Version: 2.1
Name: pjpersist
Version: 3.1.4
Summary: PostgreSQL/JSONB Persistence Backend
Home-page: https://github.com/Shoobx/pjpersist
Author: Shoobx Team
Author-email: dev@shoobx.com
License: ZPL 2.1
Keywords: postgres jsonb persistent
Classifier: Development Status :: 5 - Production/Stable
Classifier: Intended Audience :: Developers
Classifier: Programming Language :: Python
Classifier: Programming Language :: Python :: 3
Classifier: Programming Language :: Python :: 3.7
Classifier: Programming Language :: Python :: 3.8
Classifier: Programming Language :: Python :: 3.9
Classifier: Programming Language :: Python :: 3.10
Classifier: Programming Language :: Python :: 3.11
Classifier: Framework :: ZODB
Classifier: License :: OSI Approved :: Zope Public License
Classifier: Natural Language :: English
Classifier: Operating System :: OS Independent
Provides-Extra: test
Provides-Extra: zope
License-File: LICENSE.txt
